Tikdjoub/__init__.py
Tikdjoub/setup.py
tikdjoub-1.0.0.dist-info/licenses/LICENSE
tikdjoub-1.0.0.dist-info/METADATA
tikdjoub-1.0.0.dist-info/WHEEL
tikdjoub-1.0.0.dist-info/top_level.txt
tikdjoub-1.0.0.dist-info/RECORD
