Metadata-Version: 2.4
Name: tikdjoub
Version: 1.0.0
Summary: Comprehensive Python library for TikTok API signatures generation
Home-page: https://github.com/djoub/tikdjoub
Author: djoub
Author-email: djoub <benchehba@gmail.com>
License: MIT
Project-URL: Homepage, https://github.com/djoub/tikdjoub
Project-URL: Bug Tracker, https://github.com/djoub/tikdjoub/issues
Project-URL: Documentation, https://github.com/djoub/tikdjoub/wiki
Project-URL: Source Code, https://github.com/djoub/tikdjoub
Keywords: tiktok,api,signature,gorgon,ladon,argus,security,authentication
Classifier: Development Status :: 4 - Beta
Classifier: Intended Audience :: Developers
Classifier: License :: OSI Approved :: MIT License
Classifier: Programming Language :: Python :: 3
Classifier: Programming Language :: Python :: 3.6
Classifier: Programming Language :: Python :: 3.7
Classifier: Programming Language :: Python :: 3.8
Classifier: Programming Language :: Python :: 3.9
Classifier: Programming Language :: Python :: 3.10
Classifier: Programming Language :: Python :: 3.11
Classifier: Programming Language :: Python :: 3.12
Classifier: Operating System :: OS Independent
Classifier: Topic :: Software Development :: Libraries :: Python Modules
Classifier: Topic :: Internet :: WWW/HTTP
Classifier: Topic :: Security
Requires-Python: >=3.6
License-File: LICENSE
Requires-Dist: pycryptodome>=3.19.0
Provides-Extra: dev
Requires-Dist: pytest>=7.0.0; extra == "dev"
Requires-Dist: pytest-cov>=4.0.0; extra == "dev"
Requires-Dist: black>=23.0.0; extra == "dev"
Requires-Dist: flake8>=6.0.0; extra == "dev"
Dynamic: author
Dynamic: home-page
Dynamic: license-file
Dynamic: requires-python
